README.rst
setup.py
pylang/__init__.py
pylang/mains.py
pylang/utils.py
pylang.egg-info/PKG-INFO
pylang.egg-info/SOURCES.txt
pylang.egg-info/dependency_links.txt
pylang.egg-info/entry_points.txt
pylang.egg-info/top_level.txt