Metadata-Version: 1.1
Name: pylang
Version: 0.1.0
Summary: Multiple language installer
Home-page: https://github.com/harshasrinivas/pylang/
Author: Harsha Srinivas
Author-email: 95harsha95@gmail.com
License: UNKNOWN
Keywords: languages,installer,CLI,python
Platform: UNKNOWN
Classifier: Operating System :: POSIX
Classifier: Environment :: Console
Classifier: Topic :: System :: Installation/Setup
Classifier: Programming Language :: Python
Classifier: Programming Language :: Python :: 2
Classifier: Programming Language :: Python :: 3
Classifier: Programming Language :: Python :: 3.2
Classifier: Programming Language :: Python :: 3.3
Classifier: Topic :: Utilities
Classifier: Topic :: Software Development :: Libraries :: Python Modules
